pygce/__init__.py
pygce/cli.py
pygce/analysis/__init__.py
pygce/analysis/cli.py
pygce/analysis/models.py
pygce/models/__init__.py
pygce/models/bot.py
pygce/models/logger.py
pygce/models/garmin/__init__.py
pygce/models/garmin/timeline.py
pygce/models/garmin/utils.py
pygce-1.9.8.dist-info/LICENSE
pygce-1.9.8.dist-info/METADATA
pygce-1.9.8.dist-info/WHEEL
pygce-1.9.8.dist-info/entry_points.txt
pygce-1.9.8.dist-info/top_level.txt
pygce-1.9.8.dist-info/RECORD
